herald/beans.py
herald/core.py
herald/__init__.py
herald/directory.py
herald/shell.py
herald/utils.py
herald/exceptions.py
herald/probe/core.py
herald/probe/__init__.py
herald/probe/store_log.py
herald/probe/shell.py
herald/probe/store_sqlite.py
herald/remote/herald_jsonrpc.py
herald/remote/discovery.py
herald/remote/__init__.py
herald/remote/herald_jabsorbrpc.py
herald/remote/herald_xmlrpc.py
herald/transports/peer_contact.py
herald/transports/__init__.py
herald/transports/xmpp/beans.py
herald/transports/xmpp/monitor.py
herald/transports/xmpp/transport.py
herald/transports/xmpp/bot.py
herald/transports/xmpp/__init__.py
herald/transports/xmpp/directory.py
herald/transports/xmpp/utils.py
herald/transports/http/beans.py
herald/transports/http/servlet.py
herald/transports/http/transport.py
herald/transports/http/discovery_multicast.py
herald/transports/http/__init__.py
herald/transports/http/directory.py
Cohorte_Herald-0.0.3.dist-info/WHEEL
Cohorte_Herald-0.0.3.dist-info/METADATA
Cohorte_Herald-0.0.3.dist-info/RECORD
Cohorte_Herald-0.0.3.dist-info/metadata.json
Cohorte_Herald-0.0.3.dist-info/DESCRIPTION.rst
Cohorte_Herald-0.0.3.dist-info/top_level.txt
