Metadata-Version: 2.0
Name: Cohorte-Herald
Version: 0.0.3
Summary: An easy-to-use messaging framework
Home-page: https://github.com/isandlaTech/cohorte-herald
Author: Thomas Calmant
Author-email: thomas.calmant@isandlatech.com
License: Apache License 2.0
Download-URL: https://github.com/isandlaTech/cohorte-herald/archive/master.zip
Platform: UNKNOWN
Classifier: Development Status :: 3 - Alpha
Classifier: Intended Audience :: Developers
Classifier: License :: OSI Approved :: Apache Software License
Classifier: Operating System :: OS Independent
Classifier: Programming Language :: Python :: 2.7
Classifier: Programming Language :: Python :: 3
Classifier: Programming Language :: Python :: 3.2
Classifier: Programming Language :: Python :: 3.3
Classifier: Programming Language :: Python :: 3.4
Requires-Dist: iPOPO (>=0.5.7)
Requires-Dist: sleekxmpp (>=1.3.1)
Requires-Dist: requests (>=2.3.0)
